vivadb_py/__init__.py
vivadb_py/main.py
vivadb_py-0.1.1a0.dist-info/METADATA
vivadb_py-0.1.1a0.dist-info/WHEEL
vivadb_py-0.1.1a0.dist-info/entry_points.txt
vivadb_py-0.1.1a0.dist-info/RECORD
