Metadata-Version: 2.4
Name: vivadb-py
Version: 0.1.1a0
Summary: A python wrapper around [vivadb](https://github.com/AstraBert/vivadb)
Requires-Python: >=3.10
Requires-Dist: httpx>=0.28.1
